{
  "$type": "Comindware.Platform.Contracts.FormModel, Comindware.Platform.Contracts",
  "GlobalAlias": {
    "$type": "Comindware.Platform.Contracts.GlobalAlias, Comindware.Platform.Contracts",
    "Type": "Form",
    "Owner": "ShZ2501",
    "Alias": "defaultForm"
  },
  "IsDefault": true,
  "Root": {
    "$type": "Comindware.Platform.Contracts.VerticalLayoutModel, Comindware.Platform.Contracts",
    "Rows": {
      "$type": "System.Collections.Generic.List`1[[Comindware.Platform.Contracts.FormComponentModel, Comindware.Platform.Contracts]], mscorlib",
      "$values": [
        {
          "$type": "Comindware.Platform.Contracts.ActionButtonModel, Comindware.Platform.Contracts",
          "Label": {
            "$type": "Comindware.Platform.Contracts.LocalizedTextModel, Comindware.Platform.Contracts",
            "En": "API",
            "De": "API",
            "Ru": "API"
          },
          "HelpText": {
            "$type": "Comindware.Platform.Contracts.LocalizedTextModel, Comindware.Platform.Contracts"
          },
          "UserCommand": {
            "$type": "Comindware.Platform.Contracts.ActionItemView, Comindware.Platform.Contracts",
            "UserCommandGlobalAlias": {
              "$type": "Comindware.Platform.Contracts.GlobalAlias, Comindware.Platform.Contracts",
              "Type": "UserCommand",
              "Owner": "ShZ2501",
              "Alias": "API"
            },
            "Severity": "None"
          },
          "GlobalAlias": {
            "$type": "Comindware.Platform.Contracts.GlobalAlias, Comindware.Platform.Contracts",
            "Type": "FormComponent",
            "Alias": "API"
          },
          "AccessType": "Editable",
          "Width": 0,
          "Type": "ActionButton"
        },
        {
          "$type": "Comindware.Platform.Contracts.FieldComponentModel, Comindware.Platform.Contracts",
          "Label": {
            "$type": "Comindware.Platform.Contracts.LabelModel, Comindware.Platform.Contracts",
            "Hidden": false,
            "Alignment": "Top",
            "Text": {
              "$type": "Comindware.Platform.Contracts.LocalizedTextModel, Comindware.Platform.Contracts",
              "En": "parol",
              "De": "parol",
              "Ru": "parol"
            }
          },
          "FieldType": "Text",
          "Placeholder": {
            "$type": "Comindware.Platform.Contracts.LocalizedTextModel, Comindware.Platform.Contracts"
          },
          "HelpText": {
            "$type": "Comindware.Platform.Contracts.LocalizedTextModel, Comindware.Platform.Contracts"
          },
          "PropertyPath": {
            "$type": "Comindware.Platform.Contracts.GlobalAlias[], Comindware.Platform.Contracts",
            "$values": [
              {
                "$type": "Comindware.Platform.Contracts.GlobalAlias, Comindware.Platform.Contracts",
                "Type": "Attribute",
                "Owner": "ShZ2501",
                "Alias": "parol"
              }
            ]
          },
          "TextHeight": 0,
          "TextHeightAuto": false,
          "MaxLength": 0,
          "EditorType": "Multiline",
          "CreationType": "None",
          "RemovalType": "None",
          "EditType": "None",
          "ChildPropertyAlias": {
            "$type": "Comindware.Platform.Contracts.GlobalAlias, Comindware.Platform.Contracts",
            "Type": "Undefined"
          },
          "OrderPropertyAlias": {
            "$type": "Comindware.Platform.Contracts.GlobalAlias, Comindware.Platform.Contracts",
            "Type": "Undefined"
          },
          "NumberPropertyAlias": {
            "$type": "Comindware.Platform.Contracts.GlobalAlias, Comindware.Platform.Contracts",
            "Type": "Undefined"
          },
          "PrecedentPropertyAlias": {
            "$type": "Comindware.Platform.Contracts.GlobalAlias, Comindware.Platform.Contracts",
            "Type": "Undefined"
          },
          "SortingDirection": "Asc",
          "PopupFormAlias": {
            "$type": "Comindware.Platform.Contracts.GlobalAlias, Comindware.Platform.Contracts",
            "Type": "Undefined"
          },
          "GlobalAlias": {
            "$type": "Comindware.Platform.Contracts.GlobalAlias, Comindware.Platform.Contracts",
            "Type": "FormComponent",
            "Alias": "parol"
          },
          "AccessType": "Editable",
          "Width": 0,
          "Type": "FieldComponent"
        },
        {
          "$type": "Comindware.Platform.Contracts.FieldComponentModel, Comindware.Platform.Contracts",
          "Label": {
            "$type": "Comindware.Platform.Contracts.LabelModel, Comindware.Platform.Contracts",
            "Hidden": false,
            "Alignment": "Top",
            "Text": {
              "$type": "Comindware.Platform.Contracts.LocalizedTextModel, Comindware.Platform.Contracts",
              "En": "Обсуждение",
              "De": "Обсуждение",
              "Ru": "Обсуждение"
            }
          },
          "FieldType": "Conversation",
          "Placeholder": {
            "$type": "Comindware.Platform.Contracts.LocalizedTextModel, Comindware.Platform.Contracts"
          },
          "HelpText": {
            "$type": "Comindware.Platform.Contracts.LocalizedTextModel, Comindware.Platform.Contracts"
          },
          "PropertyPath": {
            "$type": "Comindware.Platform.Contracts.GlobalAlias[], Comindware.Platform.Contracts",
            "$values": [
              {
                "$type": "Comindware.Platform.Contracts.GlobalAlias, Comindware.Platform.Contracts",
                "Type": "Undefined",
                "Alias": "_conversation"
              }
            ]
          },
          "ConversationHeight": 400,
          "EditorType": "Radio",
          "CreationType": "None",
          "RemovalType": "None",
          "EditType": "None",
          "ChildPropertyAlias": {
            "$type": "Comindware.Platform.Contracts.GlobalAlias, Comindware.Platform.Contracts",
            "Type": "Undefined"
          },
          "OrderPropertyAlias": {
            "$type": "Comindware.Platform.Contracts.GlobalAlias, Comindware.Platform.Contracts",
            "Type": "Undefined"
          },
          "NumberPropertyAlias": {
            "$type": "Comindware.Platform.Contracts.GlobalAlias, Comindware.Platform.Contracts",
            "Type": "Undefined"
          },
          "PrecedentPropertyAlias": {
            "$type": "Comindware.Platform.Contracts.GlobalAlias, Comindware.Platform.Contracts",
            "Type": "Undefined"
          },
          "SortingDirection": "Asc",
          "PopupFormAlias": {
            "$type": "Comindware.Platform.Contracts.GlobalAlias, Comindware.Platform.Contracts",
            "Type": "Undefined"
          },
          "GlobalAlias": {
            "$type": "Comindware.Platform.Contracts.GlobalAlias, Comindware.Platform.Contracts",
            "Type": "FormComponent",
            "Alias": "_conversation"
          },
          "AccessType": "Readonly",
          "Width": 0,
          "Type": "FieldComponent"
        }
      ]
    },
    "GlobalAlias": {
      "$type": "Comindware.Platform.Contracts.GlobalAlias, Comindware.Platform.Contracts",
      "Type": "FormComponent",
      "Alias": "default_Root"
    },
    "AccessType": "Undefined",
    "Width": 0,
    "Type": "VerticalLayout"
  },
  "Name": "ShZ2501 - Основная форма",
  "Origination": "Undefined"
}